norsu/__init__.py
norsu/args.py
norsu/commands.py
norsu/config.py
norsu/exceptions.py
norsu/execute.py
norsu/extension.py
norsu/git.py
norsu/instance.py
norsu/main.py
norsu/terminal.py
norsu/utils.py
norsu/data/print.mk
norsu-0.6.1.dist-info/licenses/LICENSE
norsu-0.6.1.dist-info/METADATA
norsu-0.6.1.dist-info/WHEEL
norsu-0.6.1.dist-info/entry_points.txt
norsu-0.6.1.dist-info/top_level.txt
norsu-0.6.1.dist-info/RECORD
