Metadata-Version: 2.4
Name: norsu
Version: 0.6.1
Summary: PostgreSQL builds manager
Home-page: https://github.com/funbringer/norsu
Author: Dmitry Ivanov
License: MIT
Keywords: PostgreSQL,postgres,install,test
License-File: LICENSE
Requires-Dist: toml
Requires-Dist: testgres
Dynamic: author
Dynamic: description
Dynamic: description-content-type
Dynamic: home-page
Dynamic: keywords
Dynamic: license
Dynamic: license-file
Dynamic: requires-dist
Dynamic: summary
